odoo/addons/stock_picking_batch_extended/README.rst
odoo/addons/stock_picking_batch_extended/__init__.py
odoo/addons/stock_picking_batch_extended/__manifest__.py
odoo/addons/stock_picking_batch_extended/hooks.py
odoo/addons/stock_picking_batch_extended/data/batch_picking_actions_server.xml
odoo/addons/stock_picking_batch_extended/i18n/de.po
odoo/addons/stock_picking_batch_extended/i18n/es.po
odoo/addons/stock_picking_batch_extended/i18n/es_CL.po
odoo/addons/stock_picking_batch_extended/i18n/fr.po
odoo/addons/stock_picking_batch_extended/i18n/it.po
odoo/addons/stock_picking_batch_extended/i18n/pt_BR.po
odoo/addons/stock_picking_batch_extended/i18n/sl.po
odoo/addons/stock_picking_batch_extended/i18n/stock_picking_batch_extended.pot
odoo/addons/stock_picking_batch_extended/models/__init__.py
odoo/addons/stock_picking_batch_extended/models/product_product.py
odoo/addons/stock_picking_batch_extended/models/res_config_settings.py
odoo/addons/stock_picking_batch_extended/models/stock_batch_picking.py
odoo/addons/stock_picking_batch_extended/models/stock_warehouse.py
odoo/addons/stock_picking_batch_extended/readme/CONFIGURE.rst
odoo/addons/stock_picking_batch_extended/readme/CONTRIBUTORS.rst
odoo/addons/stock_picking_batch_extended/readme/CREDITS.rst
odoo/addons/stock_picking_batch_extended/readme/DESCRIPTION.rst
odoo/addons/stock_picking_batch_extended/readme/USAGE.rst
odoo/addons/stock_picking_batch_extended/report/__init__.py
odoo/addons/stock_picking_batch_extended/report/batch_report.py
odoo/addons/stock_picking_batch_extended/security/ir.model.access.csv
odoo/addons/stock_picking_batch_extended/static/batch_form_done.png
odoo/addons/stock_picking_batch_extended/static/batch_form_draft.png
odoo/addons/stock_picking_batch_extended/static/batch_form_in_progress.png
odoo/addons/stock_picking_batch_extended/static/batch_wizard.png
odoo/addons/stock_picking_batch_extended/static/picking_batch_configuration_settings.png
odoo_addon_stock_picking_batch_extended-16.0.1.1.1.2.dist-info/METADATA
odoo_addon_stock_picking_batch_extended-16.0.1.1.1.2.dist-info/WHEEL
odoo_addon_stock_picking_batch_extended-16.0.1.1.1.2.dist-info/top_level.txt
odoo_addon_stock_picking_batch_extended-16.0.1.1.1.2.dist-info/RECORD
