Metadata-Version: 2.1
Name: odoo-addon-stock_picking_batch_extended
Version: 16.0.1.1.1.2
Summary: Allows manage a lot of pickings in batch
Home-page: https://github.com/OCA/stock-logistics-workflow
Author: Camptocamp, Tecnativa, Odoo Community Association (OCA)
Author-email: support@odoo-community.org
License: AGPL-3
Classifier: Programming Language :: Python
Classifier: Framework :: Odoo
Classifier: Framework :: Odoo :: 16.0
Classifier: License :: OSI Approved :: GNU Affero General Public License v3
Classifier: Development Status :: 6 - Mature
Requires-Python: >=3.10
Requires-Dist: odoo<16.1dev,>=16.0a
